{
  "texture": "flush_completes",
  "position": "BB",
  "strategy": {
    "bet_big": {
      "frequency": 0.16,
      "hands": [
        "Nut flush",
        "Second nut flush",
        "Boats",
        "A♣X♣",
        "Strong K♣ blockers"
      ]
    },
    "bet_small": {
      "frequency": 0.14,
      "hands": [
        "Q♣J♣",
        "J♣T♣",
        "T♣9♣",
        "Top pair w/ club",
        "Second pair w/ club"
      ]
    },
    "check": {
      "frequency": 0.70,
      "hands_call": [
        "Overpairs w/ club",
        "Top pair w/ club",
        "Sets",
        "K♣X bluffcatchers"
      ],
      "hands_raise": [
        "Nut flush",
        "Boats",
        "A♣X♣ blockers"
      ],
      "hands_fold": [
        "Non-club overpairs",
        "Non-club top pair",
        "Weak Ax no club",
        "Underpairs no club",
        "Air"
      ]
    }
  }
}


